volvisdata/__init__.py
volvisdata/graph_data.py
volvisdata/market_data.py
volvisdata/market_data_prep.py
volvisdata/skew_report.py
volvisdata/svi_model.py
volvisdata/utils.py
volvisdata/vol_methods.py
volvisdata/volatility.py
volvisdata/volatility_params.py
volvisdata-1.1.1.dist-info/licenses/LICENSE
volvisdata-1.1.1.dist-info/METADATA
volvisdata-1.1.1.dist-info/WHEEL
volvisdata-1.1.1.dist-info/top_level.txt
volvisdata-1.1.1.dist-info/RECORD
