Metadata-Version: 2.4
Name: volvisdata
Version: 1.1.1
Summary: Extract implied volatility from option data.
Home-page: https://github.com/GBERESEARCH/volvisdata
Author: GBERESEARCH
Author-email: gberesearch@gmail.com
License: MIT
License-File: LICENSE
Requires-Dist: beautifulsoup4>=4.12.3
Requires-Dist: certifi>=2024.6.2
Requires-Dist: charset-normalizer>=3.3.2
Requires-Dist: frozendict>=2.4.4
Requires-Dist: html5lib>=1.1
Requires-Dist: idna>=3.7
Requires-Dist: lxml>=5.2.2
Requires-Dist: multitasking>=0.0.11
Requires-Dist: numpy>=2.0.0
Requires-Dist: pandas>=2.2.2
Requires-Dist: peewee>=3.17.5
Requires-Dist: platformdirs>=4.2.2
Requires-Dist: python-dateutil>=2.9.0.post0
Requires-Dist: pytz>=2024.1
Requires-Dist: requests>=2.32.3
Requires-Dist: scipy>=1.14.0
Requires-Dist: six>=1.16.0
Requires-Dist: soupsieve>=2.5
Requires-Dist: tzdata>=2024.1
Requires-Dist: urllib3>=2.2.2
Requires-Dist: webencodings>=0.5.1
Requires-Dist: yfinance>=0.2.40
Dynamic: license-file
